flake8_pydantic/__init__.py
flake8_pydantic/_compat.py
flake8_pydantic/_utils.py
flake8_pydantic/errors.py
flake8_pydantic/plugin.py
flake8_pydantic/py.typed
flake8_pydantic/visitor.py
flake8_pydantic-0.4.0.dist-info/LICENSE
flake8_pydantic-0.4.0.dist-info/METADATA
flake8_pydantic-0.4.0.dist-info/WHEEL
flake8_pydantic-0.4.0.dist-info/entry_points.txt
flake8_pydantic-0.4.0.dist-info/top_level.txt
flake8_pydantic-0.4.0.dist-info/RECORD
