Metadata-Version: 2.1
Name: flake8-pydantic
Version: 0.4.0
Summary: A flake8 plugin to check Pydantic related code.
Author-email: Victorien <contact@vctrn.dev>
License: MIT License
Project-URL: Homepage, https://github.com/Viicos/flake8-pydantic
Project-URL: Source, https://github.com/Viicos/flake8-pydantic
Project-URL: Changelog, https://github.com/Viicos/flake8-pydantic/blob/main/CHANGELOG.md
Classifier: Development Status :: 4 - Beta
Classifier: Operating System :: OS Independent
Classifier: Programming Language :: Python :: 3
Classifier: Programming Language :: Python :: 3 :: Only
Classifier: Programming Language :: Python :: 3.9
Classifier: Programming Language :: Python :: 3.10
Classifier: Programming Language :: Python :: 3.11
Classifier: Programming Language :: Python :: 3.12
Classifier: Programming Language :: Python :: 3.13
Classifier: Typing :: Typed
Classifier: License :: OSI Approved :: MIT License
Classifier: Intended Audience :: Developers
Classifier: Topic :: Software Development :: Libraries :: Python Modules
Classifier: Topic :: Software Development :: Quality Assurance
Classifier: Framework :: Flake8
Classifier: Framework :: Pydantic
Classifier: Framework :: Pydantic :: 2
Requires-Python: >=3.9
License-File: LICENSE
Requires-Dist: flake8
Requires-Dist: typing-extensions>=4.4.0; python_version < "3.11"
